MANIFEST.in
README.txt
rst2beamer.py
setup.cfg
setup.py
docs/.DS_Store
docs/HISTORY.txt
docs/MANUAL.pdf
docs/MANUAL.txt
docs/examples/bullets.pdf
docs/examples/bullets.rst
docs/examples/bullets_nooverlay.pdf
docs/examples/codeblocks.pdf
docs/examples/codeblocks.rst
docs/examples/columns.pdf
docs/examples/columns.rst
docs/examples/notes.pdf
docs/examples/notes.rst
docs/examples/notes_shownotes_only.pdf
docs/examples/notes_shownotes_true.pdf
docs/examples/sections.pdf
docs/examples/sections.rst
rst2beamer.egg-info/PKG-INFO
rst2beamer.egg-info/SOURCES.txt
rst2beamer.egg-info/dependency_links.txt
rst2beamer.egg-info/entry_points.txt
rst2beamer.egg-info/not-zip-safe
rst2beamer.egg-info/requires.txt
rst2beamer.egg-info/top_level.txt