Metadata-Version: 1.0
Name: rst2beamer
Version: 0.6.6
Summary: A docutils writer and script for converting restructured text to the Beamer presentation format
Home-page: http://www.agapow.net/software/rst2beamer
Author: Ryan Krauss & Paul-Michael Agapow
Author-email: ryanwkrauss@gmail.com, agapow@bbsrc.ac.uk
License: GPL
Keywords: presentation docutils rst restructured-text
Platform: UNKNOWN
Classifier: Development Status :: 5 - Production/Stable
Classifier: License :: OSI Approved :: GNU General Public License (GPL)
Classifier: Programming Language :: Python
Classifier: Topic :: Text Processing :: Markup
Classifier: Topic :: Utilities
Classifier: Topic :: Multimedia :: Graphics :: Presentation
